fika_logger/__init__.py
fika_logger/config.py
fika_logger/logger.py
fika_logger/core/__init__.py
fika_logger/core/component.py
fika_logger/core/context.py
fika_logger/core/cooldown.py
fika_logger/core/fingerprint.py
fika_logger/core/trace.py
fika_logger/formatters/__init__.py
fika_logger/formatters/github.py
fika_logger/formatters/slack.py
fika_logger/handlers/__init__.py
fika_logger/handlers/github.py
fika_logger/handlers/slack.py
fika_logger/middleware/__init__.py
fika_logger/middleware/fastapi.py
fika_logger/storage/__init__.py
fika_logger/storage/base.py
fika_logger/storage/memory.py
fika_logger/storage/mongodb.py
fika_logger/storage/redis.py
fika_logger-1.0.0.dist-info/METADATA
fika_logger-1.0.0.dist-info/WHEEL
fika_logger-1.0.0.dist-info/top_level.txt
fika_logger-1.0.0.dist-info/RECORD
