Metadata-Version: 2.4
Name: fika-logger
Version: 1.0.0
Summary: Production-grade logging library with Slack/GitHub alerting, context propagation, and deduplication
Author: FIKA Private Limited
License: Copyright (c) 2026 FIKA Private Limited. All Rights Reserved.
Project-URL: Documentation, https://github.com/fika-tech/fika-logger#readme
Project-URL: Homepage, https://github.com/fika-tech/fika-logger
Project-URL: Issues, https://github.com/fika-tech/fika-logger/issues
Project-URL: Repository, https://github.com/fika-tech/fika-logger
Keywords: logging,alerts,monitoring,slack,github,fastapi,async,context-propagation,deduplication,loguru
Classifier: Development Status :: 4 - Beta
Classifier: Intended Audience :: Developers
Classifier: License :: Other/Proprietary License
Classifier: Programming Language :: Python :: 3
Classifier: Programming Language :: Python :: 3.9
Classifier: Programming Language :: Python :: 3.10
Classifier: Programming Language :: Python :: 3.11
Classifier: Programming Language :: Python :: 3.12
Classifier: Topic :: Software Development :: Libraries :: Python Modules
Requires-Python: >=3.9
Requires-Dist: loguru>=0.7.0
Requires-Dist: motor>=3.0.0
Requires-Dist: httpx>=0.24.0
Provides-Extra: redis
Requires-Dist: redis>=4.0.0; extra == "redis"
Provides-Extra: dev
Requires-Dist: pytest>=7.0.0; extra == "dev"
Requires-Dist: pytest-asyncio>=0.21.0; extra == "dev"
Requires-Dist: pytest-cov>=4.0.0; extra == "dev"
Requires-Dist: fastapi>=0.100.0; extra == "dev"
Requires-Dist: uvicorn>=0.20.0; extra == "dev"
